cloudcoil/models/kyverno/__init__.py
cloudcoil/models/kyverno/py.typed
cloudcoil/models/kyverno/v1.py
cloudcoil/models/kyverno/v1beta1.py
cloudcoil/models/kyverno/v2.py
cloudcoil/models/kyverno/v2alpha1.py
cloudcoil/models/kyverno/v2beta1.py
cloudcoil/models/kyverno/reports/__init__.py
cloudcoil/models/kyverno/reports/v1.py
cloudcoil_models_kyverno-1.13.4.0.dist-info/METADATA
cloudcoil_models_kyverno-1.13.4.0.dist-info/WHEEL
cloudcoil_models_kyverno-1.13.4.0.dist-info/licenses/LICENSE
cloudcoil_models_kyverno-1.13.4.0.dist-info/RECORD
